licensio/__init__.py
licensio/agpl.py
licensio/apache.py
licensio/bsd.py
licensio/cc0.py
licensio/epl.py
licensio/gnu.py
licensio/lgpl.py
licensio/mit.py
licensio/wtfpl.py
licensio-1.1.0.dist-info/LICENSE
licensio-1.1.0.dist-info/METADATA
licensio-1.1.0.dist-info/WHEEL
licensio-1.1.0.dist-info/RECORD
