Metadata-Version: 2.1
Name: licensio
Version: 1.1.0
Summary: Licensio is a Python library that provides a collection of functions to generate license statements for various open source licenses. It simplifies the process of including license information in your projects by providing ready-to-use license templates.
License: MIT
Author: zayedmalick
Author-email: zayedalmalick@gmail.com
Requires-Python: >=3.11,<4.0
Classifier: License :: OSI Approved :: MIT License
Classifier: Programming Language :: Python :: 3
Classifier: Programming Language :: Python :: 3.11
